sendy/__init__.py
sendy/api.py
sendy/binder.py
sendy/exceptions.py
sendypy-0.1.5b0.dist-info/METADATA
sendypy-0.1.5b0.dist-info/RECORD
sendypy-0.1.5b0.dist-info/WHEEL
sendypy-0.1.5b0.dist-info/top_level.txt
