Metadata-Version: 2.1
Name: sendypy
Version: 0.1.5b0
Summary: Python Interface for the Sendy API
Home-page: https://bitbucket.org/netlandish/sendypy/
Author: Netlandish Inc.
Author-email: hello@netlandish.com
License: UNKNOWN
Platform: any
Classifier: Development Status :: 4 - Beta
Classifier: Intended Audience :: Developers
Classifier: Natural Language :: English
Classifier: Operating System :: OS Independent
Classifier: Programming Language :: Python
Classifier: Programming Language :: Python :: 2.7
Classifier: Programming Language :: Python :: 3.6
Classifier: Programming Language :: Python :: 3.7
Classifier: Environment :: Web Environment
Requires-Dist: requests (>=2.19.1)
